dgmrf/__init__.py
dgmrf/train.py
dgmrf/layers/__init__.py
dgmrf/layers/_conv_layer.py
dgmrf/layers/_graph_layer.py
dgmrf/losses/__init__.py
dgmrf/losses/_dgmrf_elbo.py
dgmrf/models/__init__.py
dgmrf/models/_dgmrf.py
dgmrf/models/_variational_distributions.py
dgmrf/utils/__init__.py
dgmrf/utils/_cholesky_sampling.py
dgmrf/utils/_utils.py
dgmrf-0.2.2.dist-info/licenses/LICENSE
dgmrf-0.2.2.dist-info/METADATA
dgmrf-0.2.2.dist-info/WHEEL
dgmrf-0.2.2.dist-info/top_level.txt
dgmrf-0.2.2.dist-info/RECORD
