Metadata-Version: 2.4
Name: dgmrf
Version: 0.2.2
Summary: Deep Gaussian Markov Random Fields and their extensions
Author-email: Hugo Gangloff <hugo.gangloff@inrae.fr>
Maintainer-email: Hugo Gangloff <hugo.gangloff@inrae.fr>
License: Apache License 2.0
Project-URL: Repository, https://gitlab.com/hgangloff/dgmrf
Project-URL: Documentation, https://hgangloff.gitlab.io/dgmrf/index.html
Classifier: License :: OSI Approved :: Apache Software License
Classifier: Development Status :: 4 - Beta
Classifier: Programming Language :: Python
Requires-Python: >=3.7
License-File: LICENSE
Requires-Dist: numpy
Requires-Dist: jax
Requires-Dist: optax
Requires-Dist: equinox
Provides-Extra: notebook
Requires-Dist: jupyter; extra == "notebook"
Requires-Dist: matplotlib; extra == "notebook"
Dynamic: license-file
